<?xml version="1.0" encoding="EUC-KR"?>
<RexMetaInfo>
<CarInfo>
<Rect>26,536,335,235</Rect>
</CarInfo>
<PlateInfo>
<Rect>80,688,81,26</Rect>
<PlateType>0</PlateType>
<Code>88¶ó9868</Code>
<TypeCode value="88">
<Rect>92,695,7,11</Rect>
<Rect>99,695,7,11</Rect>
</TypeCode>
<UseCode value="¶ó">
<Rect>107,695,7,10</Rect>
</UseCode>
<DigitCode value="9868">
<Rect>119,694,8,12</Rect>
<Rect>127,694,8,12</Rect>
<Rect>135,694,8,12</Rect>
<Rect>143,694,8,12</Rect>
</DigitCode>
</PlateInfo>
</RexMetaInfo>
